{"width":256,"imagePath":"NPC_ximenchuifeng_tex.png","height":256,"name":"NPC_ximenchuifeng","SubTexture":[{"width":66,"y":1,"height":91,"name":"西门吹风/头发03","x":1},{"width":21,"y":1,"height":111,"name":"西门吹风/剑","x":69},{"width":20,"y":30,"height":23,"name":"西门吹风/左手","x":144},{"width":22,"y":112,"height":25,"name":"西门吹风/左手臂02","x":112},{"width":18,"y":1,"height":27,"name":"西门吹风/左手臂01","x":144},{"width":42,"y":145,"height":11,"name":"西门吹风/裙背面","x":65},{"width":18,"y":1,"height":24,"name":"西门吹风/左脚02","x":164},{"width":18,"y":75,"height":16,"name":"西门吹风/左脚01","x":156},{"width":20,"y":139,"height":27,"name":"西门吹风/右脚02","x":124},{"width":20,"y":55,"height":18,"name":"西门吹风/右脚01","x":144},{"width":40,"y":167,"height":87,"name":"西门吹风/衣服","x":49},{"width":45,"y":114,"height":29,"name":"西门吹风/裙","x":65},{"width":37,"y":89,"height":21,"name":"西门吹风/腰带","x":92},{"width":21,"y":1,"height":83,"name":"西门吹风/长衫右","x":121},{"width":27,"y":1,"height":86,"name":"西门吹风/长衫左","x":92},{"width":15,"y":93,"height":15,"name":"西门吹风/右手","x":156},{"width":23,"y":86,"height":23,"name":"西门吹风/右手臂02","x":131},{"width":21,"y":111,"height":25,"name":"西门吹风/右手臂01","x":136},{"width":46,"y":167,"height":87,"name":"西门吹风/头发02","x":1},{"width":62,"y":94,"height":71,"name":"西门吹风/头","x":1},{"width":31,"y":167,"height":80,"name":"西门吹风/头发01","x":91}]}